poexceltool/__init__.py
poexceltool/poexcel.py
poexceltool/pokus-excel.py
poexceltool-0.1.0.dist-info/LICENSE
poexceltool-0.1.0.dist-info/METADATA
poexceltool-0.1.0.dist-info/WHEEL
poexceltool-0.1.0.dist-info/entry_points.txt
poexceltool-0.1.0.dist-info/top_level.txt
poexceltool-0.1.0.dist-info/zip-safe
poexceltool-0.1.0.dist-info/RECORD
