Metadata-Version: 2.1
Name: poexceltool
Version: 0.1.0
Summary: Convert between Excel and PO files
Home-page: https://github.com/zbyna/po-excel-tool
Author: Zbyněk Fiala
Author-email: zbynek.fiala@gmail.com
License: BSD
Keywords: translation po gettext Babel lingua
Classifier: Environment :: Console
Classifier: Intended Audience :: Developers
Classifier: License :: DFSG approved
Classifier: License :: OSI Approved :: BSD License
Classifier: Operating System :: OS Independent
Classifier: Programming Language :: Python :: 2
Classifier: Programming Language :: Python :: 2.6
Classifier: Programming Language :: Python :: 2.7
Classifier: Programming Language :: Python :: 3
Classifier: Intended Audience :: Developers
Classifier: Intended Audience :: End Users/Desktop
License-File: LICENSE
Requires-Dist: click
Requires-Dist: polib
Requires-Dist: openpyxl
Requires-Dist: tqdm
Requires-Dist: argparse ; python_version < "3.0"
